django_cache_manager/__init__.py
django_cache_manager/cache_manager.py
django_cache_manager/mixins.py
django_cache_manager/models.py
django_cache_manager/model_cache_sharing/__init__.py
django_cache_manager/model_cache_sharing/types.py
django_cache_manager/model_cache_sharing/backends/__init__.py
django_cache_manager/model_cache_sharing/backends/base.py
django_cache_manager/model_cache_sharing/backends/ipc.py
django_cache_manager/model_cache_sharing/backends/shared_memory.py
django_cache_manager-0.5.1.dist-info/DESCRIPTION.rst
django_cache_manager-0.5.1.dist-info/METADATA
django_cache_manager-0.5.1.dist-info/RECORD
django_cache_manager-0.5.1.dist-info/WHEEL
django_cache_manager-0.5.1.dist-info/metadata.json
django_cache_manager-0.5.1.dist-info/top_level.txt
