Metadata-Version: 2.0
Name: django-cache-manager
Version: 0.5.1
Summary: Cache manager for django models
Home-page: https://github.com/vijaykatam/django-cache-manager
Author: Vijay Katam
Author-email: UNKNOWN
License: UNKNOWN
Keywords: django-cache-manager
Platform: UNKNOWN
Classifier: Development Status :: 4 - Beta
Classifier: Intended Audience :: Developers
Classifier: Natural Language :: English
Classifier: Programming Language :: Python :: 2
Classifier: Programming Language :: Python :: 2.6
Classifier: Programming Language :: Python :: 2.7
Requires-Dist: Django (<1.11)
